.flake8
.travis.yml
AUTHORS
ChangeLog
README.md
pyproject.toml
setup.cfg
setup.py
tox.ini
tarball_deploy/__init__.py
tarball_deploy/main.py
tarball_deploy/workdir.py
tarball_deploy.egg-info/PKG-INFO
tarball_deploy.egg-info/SOURCES.txt
tarball_deploy.egg-info/dependency_links.txt
tarball_deploy.egg-info/entry_points.txt
tarball_deploy.egg-info/not-zip-safe
tarball_deploy.egg-info/pbr.json
tarball_deploy.egg-info/top_level.txt
tests/__init__.py
tests/test_functional.py