Metadata-Version: 2.1
Name: tarball-deploy
Version: 0.0.7
Summary: atomically deploy your code from tarballs
Home-page: https://github.com/psliwka/tarball-deploy
Author: Piotr Śliwka
Author-email: contact@psliwka.info
License: MIT
Platform: UNKNOWN
Requires-Python: >=3.6
